{
  "schema_version": "2.0",
  "date": "2026-06-18",
  "compiled_at": "2026-06-18T09:15:23.181425+00:00",
  "niche": {
    "brand_name": "Chicago Cubs Fan HQ",
    "brand_short": "Cubs",
    "content_prefix": "cubs-content",
    "platforms": [
      "x_twitter"
    ],
    "timezone": "CT",
    "photo_source": "none"
  },
  "schedule": [
    {
      "time": "7:00 AM",
      "description": "Cubs 8-6 Series Win Recap",
      "type": "Game recap"
    },
    {
      "time": "12:00 PM",
      "description": "Injury Bulletin (Palencia/Steele/Boyd/Cabrera)",
      "type": "Roster/injury"
    },
    {
      "time": "1:15 PM",
      "description": "Trade Deadline — 46 Days, Rotation + Bullpen Crisis",
      "type": "Analysis"
    },
    {
      "time": "2:30 PM",
      "description": "PCA — No. 1 All-Star Vote-Getter, 15 HR",
      "type": "Bold take/feature"
    },
    {
      "time": "3:45 PM",
      "description": "Blue Jays Series Preview — Friday 1:20 PM CT",
      "type": "Series preview"
    },
    {
      "time": "5:00 PM",
      "description": "Wild Card Watch — 39-36, 7.5 GB",
      "type": "Standings analysis"
    }
  ],
  "stories": [
    {
      "story_num": 1,
      "title": "Game Recap — Cubs 8, Rockies 6 (June 17 at Wrigley — Series Win)",
      "tier": 1,
      "status": "NEW STORY",
      "angle": "Cubs scored 7 runs in the 2nd inning and won the series 2-1 with an 8-6 victory. Dansby Swanson hit his first homer since May 18 (2-run, broke game open). PCA added his 15th HR. Javier Assad won his second straight start (5-1 on the season, 5.2 IP, 2 ER). Matt Shaw was the offensive series MVP — two triples and two RBI in the finale. Jacob Webb closed it out for his 2nd save. Cubs move to 39-36.",
      "posting_window": "7:00 AM CT",
      "x_posts": [
        {
          "label": "Post 1A",
          "text": "Cubs 8, Rockies 6. Seven-run second inning, Swanson's first homer since May 18, and PCA's 15th of the year.\n\nAssad is 5-1 with back-to-back wins. Matt Shaw had two RBI and two triples this series.\n\nCubs take it 2-1 and move to 39-36.\n\n#Cubs #GoCubs #FlyTheW",
          "posting_time": "7:00 AM CT",
          "tweet_type": "Game recap / series result",
          "hashtags": [
            "#Cubs",
            "#GoCubs",
            "#FlyTheW"
          ],
          "char_count": 257
        }
      ],
      "facebook": null,
      "article": null,
      "image_concepts": null,
      "fact_check": null,
      "research": {
        "facts": "Game Recap — Cubs 8, Rockies 6 (June 17 at Wrigley)\n**Key Facts:**\n- Final score: Cubs 8, Rockies 6 (Wednesday night, June 17, 2026 at Wrigley Field)\n- Attendance: 34,938\n- 7-run 2nd inning: Cubs went 3-for-3 with RISP; RBI contributors were Shaw, Kelly, Swanson, Suzuki, Bregman\n- Dansby Swanson: 2-run HR in the 2nd inning — first homer since May 18\n- Pete Crow-Armstrong: HR in the 4th inning — his 15th of the season\n- Javier Assad: Win (5-1), 5.2 IP, 2 ER, 5 H — second consecutive strong start\n- Jacob Webb: Save (2nd of the year), worked the 9th inning\n- Matt Shaw: Player of the Game — 2 hits, 2 RBI; had two triples across the series (4 hits in the series)\n- Series result: Cubs took 2-1 (won June 15 and 17; lost June 16)\n- Cubs record: 39-36 (was 38-36 entering the game)\n**Sources:**\n- Bleacher Nation Enhanced Box Score (Cubs 8, Rockies 6 — June 17, 2026)\n- AP Wire (syndicated at WUSA9, WRAL, Fox Sports, Times Gazette, kdhnews)\n- SI.com \"3 Takeaways After Cubs Offense Breaks Through to Crush Rockies, Take Series\"\n**Confidence:** HIGH on all game facts (multiple independent AP syndications + Bleacher Nation box score)",
        "sources": ""
      }
    },
    {
      "story_num": 2,
      "title": "Injury Bulletin — Palencia IL, Steele Throwing Monday, Boyd Delayed, Cabrera Clear",
      "tier": 1,
      "status": "NEW STORY",
      "angle": "Multiple injury updates land on the off day: Palencia on 15-day IL (elbow inflammation), Phil Maton now the closer; Steele starts throwing program Monday June 22 (earliest MLB return September); Boyd lingering shoulder soreness post-Iowa rehab, no timeline; Cabrera's hand cramp from Tuesday fully cleared by testing. Porter Hodge already done for the year (UCL surgery).",
      "posting_window": "12:00 PM CT",
      "x_posts": [
        {
          "label": "Post 2A",
          "text": "Cubs injury update:\n\nPalencia is on the 15-day IL (elbow inflammation). Phil Maton takes the closer role.\n\nSteele starts throwing this Monday. Boyd hit a shoulder snag — no timeline. Cabrera's hand cramp tests came back clean.\n\n#Cubs #MLB #CubsBaseball",
          "posting_time": "12:00 PM CT",
          "tweet_type": "Roster news / injury update",
          "hashtags": [
            "#Cubs",
            "#MLB",
            "#CubsBaseball"
          ],
          "char_count": 252
        }
      ],
      "facebook": null,
      "article": null,
      "image_concepts": null,
      "fact_check": null,
      "research": {
        "facts": "Injury Bulletin — Palencia IL, Steele Throwing Monday, Boyd Delayed, Cabrera Clear\n**Key Facts:**\n- **Daniel Palencia:** Placed on 15-day IL with right elbow inflammation on June 16, 2026. Line: 2.70 ERA, 3 saves, 19 apps, 19 K. Second IL stint (first was oblique). Gavin Hollowell recalled from Iowa as roster move. Phil Maton inherits save role. Expected return: early July at earliest.\n- **Justin Steele:** Starts his throwing program June 22 (Monday). Spent three weeks with Cubs during plyo-ball phase. One more week of plyo, then throwing for several weeks. Earliest MLB return: September (6+ weeks minimum before starting games). Left elbow surgery recovery.\n- **Matthew Boyd:** Scheduled a bullpen session after suffering shoulder soreness during Iowa rehab (shoulder, not the original knee issue). Second Iowa rehab start stalled. No new timeline established. Still on the mend from left knee surgery.\n- **Edward Cabrera:** Exited June 16 game with right-hand cramp in 5th inning. All subsequent tests came back clean and negative per Counsell (\"It's a cramp right now, as far as we can tell\"). Expected to start normally in next turn. NOT on IL.\n- **Porter Hodge:** UCL surgery April 15, 2026. 12-14 month recovery. Season over (this is a carried-forward fact; not new today).\n- **Current IL overview:** Horton (elbow surgery, season over), Steele (60-day), Taillon (hamstring), Boyd (knee/shoulder), Palencia (elbow inflammation), Hodge (UCL surgery, season done)\n**Sources:**\n- MLB Trade Rumors (Palencia IL)\n- Chicago Sun-Times (Palencia IL)\n- Daily Herald (Palencia \"bad body language\" angle)\n- MLB.com (Steele rehab update, Cabrera cramp)\n- Bleacher Nation (June 16: \"Relatively Positive Injury Updates on Matthew Boyd and Justin Steele\")\n- Cubs Crib (Boyd rehab start, Steele positive update)\n- Yardbarker (Cabrera hand cramp)\n- Craig Counsell direct quote (Cabrera): \"It's a cramp right now, as far as we can tell. All the other tests are clean and negative.\"\n**Confidence:** HIGH (Palencia, Steele, Cabrera), MEDIUM (Boyd specific timeline — multiple sources confirm delay but exact next step unclear)",
        "sources": ""
      }
    },
    {
      "story_num": 3,
      "title": "Trade Deadline — 46 Days, Rotation AND Bullpen Both in Crisis",
      "tier": 2,
      "status": "FOLLOW UP",
      "angle": "August 3 deadline is 46 days away. Rotation depleted: Horton (out for season, elbow surgery), Steele (60-day IL, September at earliest), Taillon (hamstring IL), Boyd (shoulder soreness, rehab stalled). Bullpen: Palencia (IL), Hodge (done for year). Named targets: Sandy Alcántara (Marlins, 90% trade probability, best fit includes Cubs) and Casey Mize (Tigers, breakout 2.27 ERA, $6.15M expiring deal). Jed Hoyer must move.",
      "posting_window": "1:15 PM CT",
      "x_posts": [
        {
          "label": "Post 3A",
          "text": "46 days until August 3. The Cubs' rotation is falling apart.\n\nHorton, Steele, and Taillon all on IL. Boyd delayed again. Palencia just hit the IL too.\n\nSandy Alcántara and Casey Mize are the targets. The window is closing.\n\n#Cubs #MLB #CubsBaseball",
          "posting_time": "1:15 PM CT",
          "tweet_type": "Analysis / bold take",
          "hashtags": [
            "#Cubs",
            "#MLB",
            "#CubsBaseball"
          ],
          "char_count": 248
        }
      ],
      "facebook": null,
      "article": null,
      "image_concepts": null,
      "fact_check": null,
      "research": {
        "facts": "Trade Deadline — 46 Days, Rotation AND Bullpen Both in Crisis\n**Key Facts:**\n- August 3, 2026 trade deadline (46 days from June 18)\n- Rotation IL list: Cade Horton (out for season, elbow surgery), Justin Steele (60-day IL, September at earliest), Jameson Taillon (hamstring IL), Matthew Boyd (knee/shoulder, delayed)\n- Bullpen IL: Daniel Palencia (elbow inflammation, just placed), Porter Hodge (UCL, season done)\n- Jed Hoyer confirmed shopping for starting pitchers (per June 14 pipeline notes, Hoyer confirmed)\n- **Sandy Alcántara (Marlins):** 90% trade probability per Bleacher Report; Cubs listed as best fit; No. 3/No. 4 starter profile; innings-eater; expiring deal with no long commitment\n- **Casey Mize (Tigers):** 60% trade probability; breakout 2.27 ERA in 9 starts in 2026; $6.15M expiring contract; 26 years old; Cubs among named best fits\n- Other names floated in prior pipelines: Bailey Ober, Freddy Peralta (but Brewers unlikely to sell), Tarik Skubal (Tigers ace, top target across all teams)\n**Sources:**\n- Bleacher Report (\"Skubal, Alcantara and the Top 10 Starting Pitchers on the Block\")\n- ESPN (front offices under pressure; Cubs listed as buyers)\n- Fansided (trade deadline candidate rankings)\n- Cubs Crib (early Cubs rumors, prospects as trade currency)\n**Confidence:** MEDIUM (Alcántara 90% trade probability, Mize 2.27 ERA — single analysis sources; directionally consistent across multiple trade deadline articles)",
        "sources": ""
      }
    },
    {
      "story_num": 4,
      "title": "Pete Crow-Armstrong — No. 1 NL All-Star Vote-Getter, 15 HR, Undeniable",
      "tier": 2,
      "status": "FOLLOW UP",
      "angle": "After the cycle on June 15, PCA's vote totals exploded to 1.126 million — vaulting him to first place among NL outfielders. Current season line: .276/.348/.498, 15 HR (including last night), 16 SB. Pace projects to 31 HR / 35 SB. Tied with Ohtani for NL fWAR lead (3.9). From 14th place to No. 1 in less than a week.",
      "posting_window": "2:30 PM CT",
      "x_posts": [
        {
          "label": "Post 4A",
          "text": "Pete Crow-Armstrong is now the No. 1 vote-getter among NL outfielders — 1.1 million votes and counting.\n\nThe cycle. The 15th homer last night. The .276/.348/.498 season line. 16 stolen bases.\n\nThe All-Star case has been made. Get him on that roster.\n\n#Cubs #GoCubs #CubsBaseball",
          "posting_time": "2:30 PM CT",
          "tweet_type": "Bold take / player feature",
          "hashtags": [
            "#Cubs",
            "#GoCubs",
            "#CubsBaseball"
          ],
          "char_count": 278
        }
      ],
      "facebook": null,
      "article": null,
      "image_concepts": null,
      "fact_check": null,
      "research": {
        "facts": "Pete Crow-Armstrong — No. 1 NL All-Star Vote-Getter\n**Key Facts:**\n- Pre-cycle vote total: 265,408 votes, ranked 14th among NL outfielders\n- Post-cycle vote total: 1,126,119 votes — jumped to No. 1 among NL outfielders (most recent update)\n- MLB.com headline confirmed: \"Pete Crow-Armstrong leading NL outfield vote-getter, homers in Cubs' win\"\n- Season stats (CBS Sports, through June 17 game): .276/.348/.498, 14 HR, 36 RBI, 16 SB, 44 R\n- Updated with June 17 game: 15 HR (per AP wire recap)\n- On-pace projections (CBS Sports): 31 HR, 79 RBI, 97 R, 35 SB\n- fWAR: 3.9 (per Statmuse — \"tied with Ohtani for NL lead\" per prior search result, MEDIUM)\n- Statcast: 91.6 avg exit velo, 51% hard hit rate, .366 wOBA\n- Cycle achieved June 15 — first cycle of 2026 MLB season, first reverse cycle in Cubs franchise history\n**Sources:**\n- MLB.com (vote totals, leading vote-getter headline)\n- CBS Sports (season stats)\n- AP Wire (15th HR in June 17 game)\n- SI.com (Pete Crow-Armstrong \"most slept on All-Star candidate\")\n- Marquee Sports Network (PCA reaction to voting update)\n**Confidence:** HIGH (vote totals, HR #15, stats from CBS Sports are MEDIUM — single source — but directionally consistent; 3.9 WAR from prior pipeline, not re-verified same day)",
        "sources": ""
      }
    },
    {
      "story_num": 5,
      "title": "Blue Jays Series Preview — Defending AL Pennant Winners at Wrigley, Friday 1:20 PM CT",
      "tier": 2,
      "status": "NEW STORY",
      "angle": "The Blue Jays — 2025 AL pennant winners and World Series runners-up — open a 3-game series at Wrigley tomorrow (June 19). First pitch at 1:20 PM CT. Cubs at 39-36 need to build momentum heading into the All-Star break. Probable pitchers TBD. Wrigley's summer home slate is the best chance to gain ground on both the wild card and division race.",
      "posting_window": "3:45 PM CT",
      "x_posts": [
        {
          "label": "Post 5A",
          "text": "The defending AL pennant winners come to Wrigley this weekend.\n\nCubs host the Blue Jays for three games starting Friday at 1:20 PM CT — the first of back-to-back home series before the All-Star break.\n\nCubs are 39-36. Every home game matters.\n\n#Cubs #GoCubs #ChicagoCubs",
          "posting_time": "3:45 PM CT",
          "tweet_type": "Series preview / pre-game hype",
          "hashtags": [
            "#Cubs",
            "#GoCubs",
            "#ChicagoCubs"
          ],
          "char_count": 270
        }
      ],
      "facebook": null,
      "article": null,
      "image_concepts": null,
      "fact_check": null,
      "research": {
        "facts": "Blue Jays Series Preview — Friday at Wrigley, 1:20 PM CT\n**Key Facts:**\n- 3-game home series: June 19–21 at Wrigley Field\n- Game 1: Friday June 19, 1:20 PM CT (2:20 PM ET), TV: Sportsnet + Marquee Sports Network\n- Blue Jays 2025 season: AL East division champions, AL pennant winners, World Series runners-up (per Wikipedia 2026 Blue Jays season article)\n- Blue Jays June record: 3-4 in June month (per search result snippet — partial month data, MEDIUM confidence)\n- Cubs current record: 39-36 heading into the series\n- Probable pitchers: NOT announced in any searched source\n- Series context per game-monitor: off_day=true for June 18; series starts June 19 (tomorrow)\n**Sources:**\n- CBS Sports 2026 Cubs schedule\n- MLB.com Gameday preview (Game 1 date/time confirmed)\n- Wikipedia 2026 Toronto Blue Jays season (AL champions designation)\n- Series dates cross-confirmed by multiple schedule aggregators\n**Confidence:** HIGH (series dates, first pitch time), MEDIUM (Blue Jays AL pennant winners — Wikipedia single source), LOW (Blue Jays current record — partial month stat, not used in tweet)",
        "sources": ""
      }
    },
    {
      "story_num": 6,
      "title": "Wild Card Watch — 39-36, Seven Games Back, Three Spots Available",
      "tier": 2,
      "status": "FOLLOW UP",
      "angle": "Cubs 39-36. Brewers 44-26 — 7.5 GB in the NL Central. Three NL wild card spots are available. Cubs are above .500 and in the hunt, but every game from this home stretch matters. Division gap is too wide to chase Milwaukee; wild card path is the realistic road. Blue Jays series begins the most important stretch of the first half.",
      "posting_window": "5:00 PM CT",
      "x_posts": [
        {
          "label": "Post 6A",
          "text": "Cubs standings: 39-36. Milwaukee is 44-26 — 7.5 back in the NL Central.\n\nThree NL wild card spots are available, but every game from here counts double with the division gap this wide.\n\nBlue Jays at Wrigley starting Friday. Win at home or fall behind.\n\n#Cubs #NorthSiders #MLB",
          "posting_time": "5:00 PM CT",
          "tweet_type": "Standings analysis / bold take",
          "hashtags": [
            "#Cubs",
            "#NorthSiders",
            "#MLB"
          ],
          "char_count": 276
        }
      ],
      "facebook": null,
      "article": null,
      "image_concepts": null,
      "fact_check": null,
      "research": {
        "facts": "Wild Card Watch — 39-36, 7.5 GB, Wild Card Path\n**Key Facts:**\n- Cubs: 39-36 (confirmed from game recap)\n- Brewers: 44-26 (MEDIUM — from Yahoo Sports AI standings summary)\n- Games behind Brewers: 7.5 GB (calculated: (44-39 + 36-26) / 2 = 15/2 = 7.5)\n- Three NL wild card spots: HIGH confidence (MLB expanded playoff format since 2022)\n- Cardinals: 6-game win streak per search snippet (Jordan Walker HR, 9-2 vs Mets) — MEDIUM, single AI summary\n- Cardinals exact record: NOT confirmed — omitted from tweet per protocol\n**Sources:**\n- Yahoo Sports standings (Brewers 44-26)\n- Prior pipeline confirmation of Cubs record\n- MLB playoff format (3 wild cards per league)\n**Confidence:** MEDIUM (Brewers 44-26, single AI source), HIGH (3 NL wild card spots, cubs record)",
        "sources": ""
      }
    }
  ],
  "pipeline_stats": {
    "total_stories": 6,
    "x_posts_count": 6,
    "facebook_posts_count": 0,
    "articles_count": 0,
    "image_concepts_count": 0
  },
  "validation": {
    "errors": [],
    "warnings": [],
    "missing_files": []
  }
}