{
  "schema_version": "2.0",
  "date": "2026-04-25",
  "compiled_at": "2026-04-25T11:53:17.766213+00:00",
  "niche": {
    "brand_name": "Golf Fanrecap",
    "brand_short": "GFR",
    "content_prefix": "golf-content",
    "platforms": [
      "x_twitter",
      "facebook"
    ],
    "timezone": "ET",
    "photo_source": "imagn"
  },
  "schedule": [],
  "stories": [
    {
      "story_num": 1,
      "title": "Korda's Back-to-Back 65s Put Her 7 Clear at Chevron Championship",
      "tier": 1,
      "status": "",
      "angle": "",
      "posting_window": "",
      "x_posts": [
        {
          "label": "Post 1-1",
          "text": "65-65. FOURTEEN UNDER. SEVEN SHOTS CLEAR.\n\nNelly Korda is putting on a show at The Chevron Championship.\n\nShe birdied 4 of 5 par 5s in Round 2 on a rain-soaked Memorial Park course. This major is hers to lose.\n\n#GolfFanrecap #LPGA #ChevronChampionship",
          "posting_time": "",
          "tweet_type": "",
          "hashtags": [
            "#GolfFanrecap",
            "#LPGA",
            "#ChevronChampionship"
          ],
          "char_count": 251
        },
        {
          "label": "Post 1-2",
          "text": "Nelly Korda leads The Chevron Championship by SEVEN shots after 36 holes.\n\nO'Toole and O'Keefe are second at -7. No one is close.\n\nTwo more rounds to go — but at -14, it feels like it's already over. 🏆\n\n#GolfFanrecap #LPGA #Korda",
          "posting_time": "",
          "tweet_type": "",
          "hashtags": [
            "#GolfFanrecap",
            "#LPGA",
            "#Korda"
          ],
          "char_count": 229
        }
      ],
      "facebook": {
        "long_form": "Window: 8:00 AM ET\n\nThe question entering the 2026 Chevron Championship was whether Nelly Korda could handle the pressure of being the world's best player on the game's biggest stage. Through two rounds at Memorial Park in Houston, she has answered with a resounding yes.\n\nKorda shot a second consecutive 65 on Friday to reach 14 under par, extending her lead to seven shots — a margin that speaks less to anyone else's failures than to the sheer quality of her golf. She hit 11 of 13 fairways, found 14 of 18 greens in regulation, and needed just 24 putts on a rain-soaked course that played long and difficult for most of the field. She birdied four of the five par 5s and, crucially, never let any difficult stretch of holes derail the round.\n\nRyann O'Toole shot a 68 to join amateur Farah O'Keefe at 7 under for the tournament — tied for second and seven back. The gap between Korda and the field is not just a score-line; it is a statement about where she is in her career and what this championship means to her. Korda has won this event before, and the way she has moved through Memorial Park this week has the feel of a player who belongs here.\n\nTwo rounds remain. But at 14 under with a seven-shot cushion, the Chevron Championship already feels like Korda's to lose.\n\n#GolfFanrecap | #LPGA",
        "image_caption": "",
        "posting_time": ""
      },
      "article": {
        "filename": "article-01-korda-chevron-championship-back-to-back-65.html",
        "headline": "Korda Shoots Back-to-Back 65s, Leads Chevron Championship by Seven",
        "word_count": 486
      },
      "image_concepts": [
        {
          "label": "Image",
          "raw": "Korda's Back-to-Back 65s — Chevron Championship\n\n**Concept 1A — Social (1080x1350)**\n- Type: imagn\n- Search terms: \"Nelly Korda LPGA\"\n- Scene: Korda celebrating birdie or lining up putt\n- Text overlay: \"KORDA DOMINATES: 65-65 / -14 TOTAL • 7-SHOT LEAD • CHEVRON CHAMPIONSHIP\"\n- status: not_started\n\n**Concept 1B — Article Hero (1200x630)**\n- Type: imagn\n- Search terms: \"Nelly Korda golf\"\n- Scene: Korda mid-swing or trophy celebration\n- Text overlay: \"KORDA TAKES COMMANDING 7-SHOT LEAD AT CHEVRON CHAMPIONSHIP\"\n- status: not_started\n\n---"
        }
      ],
      "fact_check": null,
      "research": null
    },
    {
      "story_num": 2,
      "title": "Fitzpatrick Brothers Storm to T2 With 65 in Alternate Shot — One Back at Zurich",
      "tier": 1,
      "status": "",
      "angle": "",
      "posting_window": "",
      "x_posts": [
        {
          "label": "Post 2-1",
          "text": "The Fitzpatrick brothers were 6 shots back entering the alternate shot round.\n\nThey shot a 7-under 65. 6 birdies. An eagle. Matt chipped in on 18.\n\nNow they're ONE shot off the lead at the Zurich Classic. GAME ON.\n\n#GolfFanrecap #ZurichClassic #PGATour",
          "posting_time": "",
          "tweet_type": "",
          "hashtags": [
            "#GolfFanrecap",
            "#ZurichClassic",
            "#PGATour"
          ],
          "char_count": 252
        },
        {
          "label": "Post 2-2",
          "text": "Leaderboard after 36 holes at the Zurich Classic:\n\n-16: Smalley/Springer (leaders)\n-15: Fitzpatricks 🏴󠁧󠁢󠁥󠁮󠁧󠁿🏴󠁧󠁢󠁥󠁮󠁧󠁿 (65 today)\n-15: Thompson/Eckroat\n-15: Horschel/Hoge\n\nOne shot between 1st and 4th. Saturday in New Orleans should be 🔥\n\n#GolfFanrecap #ZurichClassic",
          "posting_time": "",
          "tweet_type": "",
          "hashtags": [
            "#GolfFanrecap",
            "#ZurichClassic"
          ],
          "char_count": 264
        }
      ],
      "facebook": {
        "long_form": "Window: 10:30 AM ET\n\nIf the Fitzpatrick brothers were feeling the pressure of being six shots behind entering Friday's alternate shot round at the Zurich Classic, they did a remarkable job of hiding it.\n\nMatt and Alex Fitzpatrick — the older brother a three-time PGA Tour winner and current World No. 3, the younger a promising professional in his own right — produced what may have been the round of the tournament through 36 holes. Their 7-under 65 in the alternate shot format included six birdies, an eagle, and just one bogey, with Matt rolling in a chip-in birdie on the par-5 18th hole as the signature moment of an outstanding performance.\n\nThe result moved them from well off the pace to a share of second place at 15 under — just one stroke behind leaders Alex Smalley and Hayden Springer, who shot a 70 in the alternate shot round to hold at 16 under. Davis Thompson/Austin Eckroat and Billy Horschel/Tom Hoge are also at 15 under, making for an exceptionally tight leaderboard heading into Saturday's best ball Round 3.\n\nThe Fitzpatricks have proven they can compete in every format. Their path to the title runs through one of the most competitive Saturday rounds TPC Louisiana is likely to see.\n\n#GolfFanrecap | #PGATour",
        "image_caption": "",
        "posting_time": ""
      },
      "article": {
        "filename": "article-02-fitzpatrick-brothers-zurich-classic-65-alternate-shot.html",
        "headline": "Fitzpatrick Brothers Shoot 65 in Alternate Shot, Move to T2 at Zurich Classic",
        "word_count": 520
      },
      "image_concepts": [
        {
          "label": "Image",
          "raw": "Fitzpatrick Brothers — Zurich T2\n\n**Concept 2A — Social (1080x1350)**\n- Type: imagn\n- Search terms: \"Matt Fitzpatrick golf\"\n- Scene: Fitzpatrick celebrating or fist pump\n- Text overlay: \"FITZPATRICKS STORM INTO T2 / 65 IN ALT SHOT • ONE BACK AT ZURICH CLASSIC\"\n- status: not_started\n\n**Concept 2B — Article Hero (1200x630)**\n- Type: imagn\n- Search terms: \"Matt Fitzpatrick PGA Tour\"\n- Scene: Fitzpatrick playing approach or celebrating\n- Text overlay: \"FITZPATRICK BROTHERS CHARGE TO ZURICH CLASSIC T2 WITH STUNNING 65\"\n- status: not_started\n\n---"
        }
      ],
      "fact_check": null,
      "research": null
    },
    {
      "story_num": 3,
      "title": "Koepka and Lowry Miss the Cut — Zurich Classic Heartbreak for High-Profile Team",
      "tier": 1,
      "status": "",
      "angle": "",
      "posting_window": "",
      "x_posts": [
        {
          "label": "Post 3-1",
          "text": "Brooks Koepka and Shane Lowry missed the Zurich Classic cut by ONE stroke.\n\nBogeys on par 3s Nos. 3 and 17 cost them in the alternate shot round.\n\nOne of the most anticipated pairings of the week — gone by Friday.\n\n#GolfFanrecap #ZurichClassic #PGATour",
          "posting_time": "",
          "tweet_type": "",
          "hashtags": [
            "#GolfFanrecap",
            "#ZurichClassic",
            "#PGATour"
          ],
          "char_count": 252
        },
        {
          "label": "Post 3-2",
          "text": "Koepka and Lowry went home from the Zurich Classic one shot too few.\n\nGreat friends. Two major winners. A partnership built at Grove XXIII.\n\nSometimes golf doesn't care about storylines. They needed -10. They shot -9.\n\n#GolfFanrecap #ZurichClassic #PGATour",
          "posting_time": "",
          "tweet_type": "",
          "hashtags": [
            "#GolfFanrecap",
            "#ZurichClassic",
            "#PGATour"
          ],
          "char_count": 256
        }
      ],
      "facebook": {
        "long_form": "Window: 1:00 PM ET\n\nThe storyline wrote itself — two major champions, close friends, a partnership formed on the putting greens of an exclusive Florida club, teaming up to chase one of golf's most unique team titles at the Zurich Classic of New Orleans. The only thing missing was the ending the story deserved.\n\nBrooks Koepka and Shane Lowry missed the cut by a single stroke on Friday, finishing the tournament at 9 under after the cut fell at 10 under. Their alternate shot round on Friday featured five birdies — enough in most circumstances — but bogeys on the par-3 third and par-3 17th proved decisive. One stroke separated their week from the weekend.\n\nThe pairing had been built with genuine excitement. Koepka's four major championships and Lowry's Open Championship title gave the team enormous credentials, and their friendship added a natural chemistry that many team pairings lack. But chemistry and credentials only carry you so far when the cards don't fall your way. Koepka had just one birdie in Thursday's best ball round, and Lowry's strong front nine on Friday stalled coming home.\n\nIt is a difficult exit from a tournament they had every reason to believe they could contend in. The Zurich Classic is one of golf's most genuinely fun events, and Koepka and Lowry will almost certainly be back. This year's story, though, ends here.\n\n#GolfFanrecap | #PGATour",
        "image_caption": "",
        "posting_time": ""
      },
      "article": {
        "filename": "article-03-koepka-lowry-miss-zurich-classic-cut.html",
        "headline": "Koepka and Lowry Miss Zurich Classic Cut by One Stroke — Bogeys on Par 3s Prove Costly",
        "word_count": 564
      },
      "image_concepts": [
        {
          "label": "Image",
          "raw": "Koepka/Lowry Miss Cut\n\n**Concept 3A — Social (1080x1350)**\n- Type: imagn\n- Search terms: \"Brooks Koepka golf\"\n- Scene: Koepka walking or looking at scorecard\n- Text overlay: \"MISSED BY ONE: KOEPKA + LOWRY / -9 AT ZURICH — CUT WAS -10\"\n- status: not_started\n\n**Concept 3B — Article Hero (1200x630)**\n- Type: imagn\n- Search terms: \"Shane Lowry golf\"\n- Scene: Lowry on course or putting\n- Text overlay: \"KOEPKA & LOWRY MISS ZURICH CLASSIC CUT BY ONE SHOT\"\n- status: not_started\n\n---"
        }
      ],
      "fact_check": null,
      "research": null
    },
    {
      "story_num": 4,
      "title": "Zurich Classic R3 Preview — Smalley/Springer Lead by 1 as Best Ball Resumes",
      "tier": 2,
      "status": "NEW STORY",
      "angle": "",
      "posting_window": "",
      "x_posts": [
        {
          "label": "Post 4",
          "text": "Best ball is back at the Zurich Classic on Saturday.\n\nFour teams within ONE shot of the lead. Fitzpatricks love this format.\n\nSmalley/Springer need to hold off three red-hot teams in Round 3.\n\nThis should be a great day of golf. #GolfFanrecap #ZurichClassic #PGATour",
          "posting_time": "",
          "tweet_type": "",
          "hashtags": [
            "#GolfFanrecap",
            "#ZurichClassic",
            "#PGATour"
          ],
          "char_count": 266
        }
      ],
      "facebook": {
        "long_form": "Window: 3:30 PM ET\n\nFour teams. One shot separating them. And Saturday's format is the one that typically sends scores flying.\n\nThe Zurich Classic of New Orleans returns to best ball format for Round 3 on Saturday, and the leaderboard after 36 holes could not be more conducive to a compelling day at TPC Louisiana. Alex Smalley and Hayden Springer hold the lead at 16 under par, but three teams sit just one shot behind at 15 under: Matt and Alex Fitzpatrick, Davis Thompson/Austin Eckroat, and Billy Horschel/Tom Hoge.\n\nThe Fitzpatricks may be the most dangerous challengers of the three. Matt is World No. 3 and won the RBC Heritage at Hilton Head just last week. In best ball format — where both players play their own ball and the team takes the lower score — his ceiling is exceptionally high. Alex adds the kind of steady presence that keeps the team from giving shots back.\n\nThompson and Eckroat have also been consistent across both rounds, and Horschel's experience in big moments makes their team dangerous too. Smalley and Springer, for their part, know they are leading and will need to find a gear in best ball to hold off the charge.\n\nWith $9.5 million on the line and Sunday's alternate shot finale still to come, Saturday shapes up as one of the most compelling days of the PGA Tour season.\n\n#GolfFanrecap | #PGATour",
        "image_caption": "",
        "posting_time": ""
      },
      "article": {
        "filename": "article-04-zurich-classic-r3-preview-smalley-springer.html",
        "headline": "Zurich Classic R3 Preview: Smalley and Springer Lead by One as Best Ball Delivers Drama",
        "word_count": 566
      },
      "image_concepts": [
        {
          "label": "Image",
          "raw": "Zurich Classic R3 Preview\n\n**Concept 4A — Social (1080x1350)**\n- Type: gemini\n- Mode: base_only\n- Prompt: Dark green golf course background with TPC Louisiana bayou aesthetic. Spanish moss trees silhouetted at edges. Deep green with gold highlights. Clean space for leaderboard text overlay. Professional sports graphic. No faces, no logos.\n- Text overlay: \"ZURICH CLASSIC R3 / SMALLEY-SPRINGER -16 / FITZPATRICKS -15 / BEST BALL SATURDAY\"\n- status: not_started\n\n---"
        }
      ],
      "fact_check": null,
      "research": null
    },
    {
      "story_num": 5,
      "title": "LIV Golf Virginia Preview — Rahm Returns as Defending Mexico City Winner",
      "tier": 2,
      "status": "",
      "angle": "",
      "posting_window": "",
      "x_posts": [
        {
          "label": "Post 5",
          "text": "Jon Rahm wins LIV Mexico City by SIX shots. Now he heads to Virginia.\n\nLIV Golf Virginia returns to Trump National Golf Club DC, May 8-10.\n\nRahm's in form. Legion XIII is rolling. And it's one of LIV's most popular stops.\n\n#GolfFanrecap #LIVGolf #Rahm",
          "posting_time": "",
          "tweet_type": "",
          "hashtags": [
            "#GolfFanrecap",
            "#LIVGolf",
            "#Rahm"
          ],
          "char_count": 251
        }
      ],
      "facebook": {
        "long_form": "Window: 6:00 PM ET\n\nJon Rahm is not a man who lacks for motivation. But if you needed proof of it, consider this: he closed the LIV Golf Mexico City event with a bogey-free 7-under 64, won by six shots, and immediately turned the conversation to what comes next.\n\nWhat comes next is LIV Golf Virginia, scheduled for May 8-10 at Trump National Golf Club Washington D.C. in Sterling, Virginia — one of the tour's most popular stops and a venue that draws a competitive, engaged crowd from the Washington metropolitan area. For LIV, it is a flagship event. For Rahm, it is another opportunity to extend what has been a dominant stretch of form.\n\nLegion XIII, Rahm's team, claimed their third consecutive team title in Mexico City — a statement of consistency that transcends any individual result. The format of LIV, where team points matter alongside individual standings, has given Rahm and his roster a sense of collective purpose that clearly motivates the entire squad.\n\nThe field in Virginia will include Joaquin Niemann of Torque GC, who won the individual title at Virginia in 2025, and Bryson DeChambeau's Crushers GC, who claimed the team championship at the event a year ago. Both will be looking to defend. Rahm will be looking to keep his momentum rolling. And the fans in Northern Virginia will get to decide who deserves to be called the best in LIV Golf right now.\n\n#GolfFanrecap | #LIVGolf",
        "image_caption": "",
        "posting_time": ""
      },
      "article": {
        "filename": "article-05-liv-golf-virginia-preview-rahm-legion-xiii.html",
        "headline": "LIV Golf Virginia Preview: Rahm Arrives With Momentum After Mexico City Dominance",
        "word_count": 503
      },
      "image_concepts": [
        {
          "label": "Image",
          "raw": "LIV Golf Virginia Preview\n\n**Concept 5A — Social (1080x1350)**\n- Type: imagn\n- Search terms: \"Jon Rahm LIV Golf\"\n- Scene: Rahm celebrating win or mid-swing\n- Text overlay: \"RAHM RETURNS: LIV VIRGINIA / MAY 8-10 • TRUMP NATIONAL DC • LEGION XIII ROLLING\"\n- status: not_started"
        }
      ],
      "fact_check": null,
      "research": null
    }
  ],
  "pipeline_stats": {
    "total_stories": 5,
    "x_posts_count": 8,
    "facebook_posts_count": 5,
    "articles_count": 5,
    "image_concepts_count": 5
  },
  "validation": {
    "errors": [],
    "warnings": [
      "Story 1: No posting window specified",
      "Story 2: No posting window specified",
      "Story 3: No posting window specified",
      "Story 4: No posting window specified",
      "Story 5: No posting window specified"
    ],
    "missing_files": []
  }
}