{
  "schema_version": "2.0",
  "date": "2026-06-01",
  "compiled_at": "2026-06-01T12:26:52.617833+00:00",
  "niche": {
    "brand_name": "Tennis Fanrecap",
    "brand_short": "TFR",
    "content_prefix": "tennis-content",
    "platforms": [
      "x_twitter",
      "facebook"
    ],
    "timezone": "ET",
    "photo_source": "imagn"
  },
  "schedule": [],
  "stories": [
    {
      "story_num": 1,
      "title": "Fonseca def. Ruud 7-5, 7-6(8), 5-7, 6-2 — First Brazilian RG QF since Kuerten",
      "tier": 0,
      "status": "",
      "angle": "",
      "posting_window": "",
      "x_posts": [
        {
          "label": "Post 1-1",
          "text": "Fonseca 19 beats Ruud 7-5 7-6(8) 5-7 6-2 to reach his first Grand Slam QF. First Brazilian man in the Roland Garros quarterfinals since Kuerten in 2004. From beating Djokovic to beating Ruud — what a fortnight. #RolandGarros #TennisFanrecap #FrenchOpen #Fonseca",
          "posting_time": "",
          "tweet_type": "",
          "hashtags": [
            "#RolandGarros",
            "#TennisFanrecap",
            "#FrenchOpen",
            "#Fonseca"
          ],
          "char_count": 261
        },
        {
          "label": "Post 1-2",
          "text": "At 19, Fonseca has beaten No. 3 Djokovic AND two-time RG finalist Ruud in the same Roland Garros. He joins Agassi and Alcaraz in the list of teenage Roland Garros QF players. Brazil's clay legacy lives. #RolandGarros #TennisFanrecap #FrenchOpen #Fonseca",
          "posting_time": "",
          "tweet_type": "",
          "hashtags": [
            "#RolandGarros",
            "#TennisFanrecap",
            "#FrenchOpen",
            "#Fonseca"
          ],
          "char_count": 253
        }
      ],
      "facebook": {
        "long_form": "**Window:** 8:00 AM ET\n\nJoão Fonseca is writing history at Roland Garros, and he is only 19 years old.\n\nThe Brazilian teenager defeated two-time Roland Garros finalist Casper Ruud 7-5, 7-6(8), 5-7, 6-2 in a nearly four-hour battle on Day 8, reaching his first Grand Slam quarterfinal. To put this in perspective: the last Brazilian man to reach the Roland Garros quarterfinals was Gustavo Kuerten — in 2004. Fonseca was not yet two years old when Kuerten last played on these courts as a contender.\n\nThis is also his second straight victory over a top opponent this tournament. He stunned No. 3 Novak Djokovic in the third round, then knocked out two-time finalist Ruud. The Roland Garros draw opened up after Sinner's exit, and Fonseca walked right through the door.\n\nHe now faces 20-year-old Jakub Mensik of the Czech Republic in Tuesday's quarterfinal — a matchup of the two youngest players left in the men's draw. Whatever the result, Brazilian tennis fans have found their next great clay champion.\n\nWho else is loving the Fonseca storyline at this Roland Garros?\n\n---",
        "image_caption": "**Window:** 8:30 AM ET\n\nJoão Fonseca. 19 years old. Grand Slam quarterfinal. First Brazilian man in the Roland Garros last eight since Kuerten in 2004. The kid keeps delivering.",
        "posting_time": ""
      },
      "article": {
        "filename": "article-01-fonseca-ruud-first-brazilian-rg-qf-kuerten.html",
        "headline": "Fonseca Becomes First Brazilian Man in Roland Garros Quarterfinal Since Kuerten",
        "word_count": 504
      },
      "image_concepts": [
        {
          "label": "Image",
          "raw": "Fonseca def. Ruud\n\n**Social Image (1080x1350 vertical)**\nSearch term: \"Joao Fonseca Roland Garros\"\nCredit: (Imagn Images)\nStatus: not_started\n\n**Article Hero (1200x630 landscape)**\nSearch term: \"Joao Fonseca Roland Garros\"\nCredit: (USA TODAY Sports Images)\nStatus: not_started\n\n---"
        }
      ],
      "fact_check": null,
      "research": null
    },
    {
      "story_num": 2,
      "title": "Men's QF Set — Zverev vs Jodar (19), Fonseca (19) vs Mensik (20)",
      "tier": 0,
      "status": "",
      "angle": "",
      "posting_window": "",
      "x_posts": [
        {
          "label": "Post 2-1",
          "text": "Three of the four Roland Garros men's QF spots belong to players aged 19-20. Jodar 19, Fonseca 19, Mensik 20 — plus No. 2 Zverev 27. The youngest men's QF field at a Grand Slam in years. Tennis is thriving. #RolandGarros #TennisFanrecap #FrenchOpen #NextGen",
          "posting_time": "",
          "tweet_type": "",
          "hashtags": [
            "#RolandGarros",
            "#TennisFanrecap",
            "#FrenchOpen",
            "#NextGen"
          ],
          "char_count": 257
        },
        {
          "label": "Post 2-2",
          "text": "Jodar 19 was down 2 sets to Carreño Busta and won the last three 6-1 6-2 6-2. First Grand Slam QF. Faces No. 2 Zverev on Tuesday. The teenage takeover of Roland Garros 2026 is real. #RolandGarros #TennisFanrecap #FrenchOpen #Jodar",
          "posting_time": "",
          "tweet_type": "",
          "hashtags": [
            "#RolandGarros",
            "#TennisFanrecap",
            "#FrenchOpen",
            "#Jodar"
          ],
          "char_count": 230
        }
      ],
      "facebook": {
        "long_form": "**Window:** 10:30 AM ET\n\nThree of the four Roland Garros men's quarterfinal spots belong to teenagers or 20-year-olds. Let that sink in.\n\nJoão Fonseca (19, Brazil) vs. Jakub Mensik (20, Czech Republic). Rafael Jodar (19, Spain) vs. Alexander Zverev (27, Germany). The youngest Grand Slam quarterfinal field for men in years — and it was earned, not given.\n\nMensik defeated No. 12 Andrey Rublev in a five-set thriller (6-3, 7-6, 4-6, 2-6, 6-3), becoming the youngest Czech man in a Grand Slam quarterfinal since Ivan Lendl in 1980. Jodar came back from two sets down to beat Pablo Carreño Busta 4-6, 4-6, 6-1, 6-2, 6-2 — a stunning reversal in front of the Paris crowd.\n\nZverev is the experienced favorite, but after what we have seen from Sinner, Djokovic, and Alcaraz all falling before the quarterfinals, the draw is wide open. Both quarterfinals are scheduled for Tuesday on Philippe-Chatrier.\n\nTennis is not in crisis. Tennis is thriving. Are you excited about the new generation taking over Roland Garros?\n\n---",
        "image_caption": "**Window:** 11:00 AM ET\n\nFonseca (19), Jodar (19), Mensik (20), Zverev (27). Your Roland Garros men's quarterfinal lineup. Three of four spots filled by players under 21. The next era of men's tennis arrived on the biggest clay court in the world.",
        "posting_time": ""
      },
      "article": {
        "filename": "article-02-mens-qf-generation-z-roland-garros-2026.html",
        "headline": "Generation Z Takes Over Roland Garros: Three Players Under 21 in Men's Quarterfinals",
        "word_count": 583
      },
      "image_concepts": [
        {
          "label": "Image",
          "raw": "Men's QF — Gen Z\n\n**Social Image 1 (1080x1350 vertical)**\nSearch term: \"Rafael Jodar Roland Garros\"\nCredit: (Imagn Images)\nStatus: not_started\n\n**Social Image 2 (1080x1350 vertical)**\nSearch term: \"Jakub Mensik Roland Garros\"\nCredit: (Imagn Images)\nStatus: not_started\n\n---"
        }
      ],
      "fact_check": null,
      "research": null
    },
    {
      "story_num": 3,
      "title": "Sabalenka vs Osaka — Day 9 R16 Headliner on Philippe-Chatrier",
      "tier": 0,
      "status": "",
      "angle": "",
      "posting_window": "",
      "x_posts": [
        {
          "label": "Post 3-1",
          "text": "Sabalenka vs Osaka on Chatrier tonight — the biggest match of Week 2. Sabalenka seeking the title she's never won. Osaka's first Paris R16 since 2019. Sabalenka won their Madrid clay match 5 weeks ago. #RolandGarros #TennisFanrecap #FrenchOpen #Sabalenka",
          "posting_time": "",
          "tweet_type": "",
          "hashtags": [
            "#RolandGarros",
            "#TennisFanrecap",
            "#FrenchOpen",
            "#Sabalenka"
          ],
          "char_count": 254
        },
        {
          "label": "Post 3-2",
          "text": "Naomi Osaka: ranked No. 135 in Jan 2025, now seeded No. 16 at Roland Garros and in her first Paris R16 since 2019. Faces No. 1 Sabalenka tonight on Chatrier. This is what a comeback looks like. #RolandGarros #TennisFanrecap #FrenchOpen #Osaka",
          "posting_time": "",
          "tweet_type": "",
          "hashtags": [
            "#RolandGarros",
            "#TennisFanrecap",
            "#FrenchOpen",
            "#Osaka"
          ],
          "char_count": 242
        }
      ],
      "facebook": {
        "long_form": "**Window:** 3:00 PM ET\n\nTonight on Philippe-Chatrier, the most compelling match of Roland Garros Week 2 takes center stage: World No. 1 Aryna Sabalenka against Naomi Osaka.\n\nThe numbers tell part of the story. Sabalenka reached this round of 16 by recording her historic 100th win as world No. 1, shutting out Daria Kasatkina 6-0, 7-5 in the previous round. She has never won Roland Garros, and this deep run is as close as she has come. Osaka, meanwhile, is playing her first Roland Garros round of 16 since 2019 — her return to the top of the game has been one of the tennis stories of 2026.\n\nThe two met just five weeks ago in Madrid, also on clay, and Sabalenka won that match. But a round of 16 at Roland Garros is a different kind of occasion.\n\nThe winner faces either Anastasia Potapova or Anna Kalinskaya in the quarterfinal. For both players, this match matters enormously.\n\nWe will bring you the result as soon as it comes in. Who are you rooting for tonight?\n\n---",
        "image_caption": "**Window:** 4:00 PM ET\n\nSabalenka vs Osaka. Tonight. Philippe-Chatrier. World No. 1 who has never won Roland Garros. A comeback champion playing her first Paris R16 since 2019. One of them advances to the quarterfinal. The stakes don't get bigger than this in Week 2.",
        "posting_time": ""
      },
      "article": {
        "filename": "article-03-sabalenka-osaka-roland-garros-r16-preview.html",
        "headline": "Sabalenka vs Osaka: The Roland Garros R16 Showdown That Defines Week Two",
        "word_count": 547
      },
      "image_concepts": [
        {
          "label": "Image",
          "raw": "Sabalenka vs Osaka\n\n**Social Image (1080x1350 vertical)**\nSearch term: \"Aryna Sabalenka Roland Garros\"\nCredit: (Imagn Images)\nStatus: not_started\n\n**Article Hero (1200x630 landscape)**\nSearch term: \"Naomi Osaka Roland Garros\"\nCredit: (USA TODAY Sports Images)\nStatus: not_started\n\n---"
        }
      ],
      "fact_check": null,
      "research": null
    },
    {
      "story_num": 4,
      "title": "Women's Day 9 — Svitolina, Andreeva, Cirstea All Advance to QF",
      "tier": 0,
      "status": "",
      "angle": "",
      "posting_window": "",
      "x_posts": [
        {
          "label": "Post 4",
          "text": "Women's R16: Svitolina def. Bencic 4-6 6-4 6-0. Andreeva def. Teichmann 6-3 6-2. Cirstea def. Wang 6-3 7-6. QF matchups: Svitolina vs Kostyuk (all-Ukraine), Andreeva vs Cirstea. #RolandGarros #TennisFanrecap #FrenchOpen #WTA",
          "posting_time": "",
          "tweet_type": "",
          "hashtags": [
            "#RolandGarros",
            "#TennisFanrecap",
            "#FrenchOpen",
            "#WTA"
          ],
          "char_count": 224
        }
      ],
      "facebook": {
        "long_form": "**Window:** 12:30 PM ET\n\nThe Roland Garros women's quarterfinal field is taking shape, and Day 9 delivered three results worth marking on your calendar.\n\nElina Svitolina, the No. 7 seed from Ukraine, defeated No. 11 Belinda Bencic 4-6, 6-4, 6-0 in a match that showed her resilience — dropping the first set, then dominating the final set. She now faces a quarterfinal against her compatriot Marta Kostyuk. An all-Ukraine Roland Garros quarterfinal is something no one predicted at the start of the tournament.\n\nMirra Andreeva continued her brilliant run, defeating Jil Teichmann 6-3, 6-2 to set up a quarterfinal against Sorana Cirstea. And Cirstea — 36 years old, playing what she has called her final season — defeated Wang Xiyu 6-3, 7-6 to keep her remarkable Paris run alive.\n\nThree quarterfinalists confirmed. Two more battles, including Sabalenka vs Osaka tonight, still to come. Which of these women do you see making the final?\n\n---",
        "image_caption": "**Window:** 1:00 PM ET\n\nRoland Garros women's QF confirmed: Svitolina vs Kostyuk (all-Ukraine), Andreeva vs Cirstea (36, final season). Plus Sabalenka/Osaka winner and Potapova/Kalinskaya winner still to be decided. The draw has never been more wide open.",
        "posting_time": ""
      },
      "article": {
        "filename": "article-04-women-day9-svitolina-andreeva-cirstea-r16.html",
        "headline": "Women's Day 9 Round-Up: Svitolina, Andreeva, Cirstea Advance to Roland Garros Quarterfinals",
        "word_count": 489
      },
      "image_concepts": [
        {
          "label": "Image",
          "raw": "Women's Day 9 Round-Up\n\n**Social Image (1080x1350 vertical)**\nSearch term: \"Elina Svitolina Roland Garros\"\nCredit: (Imagn Images)\nStatus: not_started\n\n**Article Hero (1200x630 landscape)**\nSearch term: \"Sorana Cirstea Roland Garros\"\nCredit: (USA TODAY Sports Images)\nStatus: not_started\n\n---"
        }
      ],
      "fact_check": null,
      "research": null
    },
    {
      "story_num": 5,
      "title": "\"New-Look\" Tiafoe — Day 9 R16 vs Arnaldi After Dramatic R3 Comeback",
      "tier": 0,
      "status": "",
      "angle": "",
      "posting_window": "",
      "x_posts": [
        {
          "label": "Post 5",
          "text": "Tiafoe rallied from 2 sets down to beat Faria, told his opponent \"you're not hard, bro,\" and is now in the Roland Garros R16 vs Arnaldi. Day 9 match of the day. The new-look Tiafoe is here. #RolandGarros #TennisFanrecap #FrenchOpen #Tiafoe",
          "posting_time": "",
          "tweet_type": "",
          "hashtags": [
            "#RolandGarros",
            "#TennisFanrecap",
            "#FrenchOpen",
            "#Tiafoe"
          ],
          "char_count": 239
        }
      ],
      "facebook": {
        "long_form": "**Window:** 6:00 PM ET\n\nFrances Tiafoe's Roland Garros run has been everything: dramatic comebacks, fiery confrontations, and what the official Roland Garros website called a \"new-look\" version of the American.\n\nIn the third round against Portugal's Jaime Faria, Tiafoe was on the brink. Down two sets, in danger of an early exit, he rallied to win 4-6, 6-7, 7-6, 6-1, 6-2 in a match so heated that the umpire had to step in to separate the two players. Tiafoe's line to Faria — \"Don't act like you're tough. You're not hard, bro. Just play\" — instantly circulated online.\n\nNow in the round of 16 against Matteo Arnaldi of Italy, Tiafoe is in his best position at Roland Garros in years. The official site named his Day 9 encounter the \"Match of the Day\" — not just because of the stakes, but because of the player showing up to compete.\n\nRoland Garros has a way of creating stories. Tiafoe is writing one right now. Are you following his run in Paris?\n\n---",
        "image_caption": "**Window:** 7:00 PM ET\n\nTiafoe. Down 2 sets. Came back. Won. Said what he said. And is now in the Roland Garros Round of 16. Day 9 Match of the Day. The new-look Tiafoe is very much in this tournament.",
        "posting_time": ""
      },
      "article": {
        "filename": "article-05-tiafoe-arnaldi-day9-roland-garros-r16.html",
        "headline": "The New-Look Tiafoe Makes His Case at Roland Garros",
        "word_count": 447
      },
      "image_concepts": [
        {
          "label": "Image",
          "raw": "Tiafoe\n\n**Social Image (1080x1350 vertical)**\nSearch term: \"Frances Tiafoe Roland Garros\"\nCredit: (Imagn Images)\nStatus: not_started"
        }
      ],
      "fact_check": null,
      "research": null
    }
  ],
  "pipeline_stats": {
    "total_stories": 5,
    "x_posts_count": 8,
    "facebook_posts_count": 5,
    "articles_count": 5,
    "image_concepts_count": 5
  },
  "validation": {
    "errors": [],
    "warnings": [
      "Story 1: No posting window specified",
      "Story 2: No posting window specified",
      "Story 3: No posting window specified",
      "Story 4: No posting window specified",
      "Story 5: No posting window specified"
    ],
    "missing_files": []
  }
}